AUTHORS
CHANGES
COPYING
MANIFEST.in
README.md
pyerconf.py
sample.cfg
setup.py
pyerconf.egg-info/PKG-INFO
pyerconf.egg-info/SOURCES.txt
pyerconf.egg-info/dependency_links.txt
pyerconf.egg-info/requires.txt
pyerconf.egg-info/top_level.txt
test/test01.py