Metadata-Version: 1.0
Name: pyerconf
Version: 0.1.0
Summary: Pythonic Hierarchical Configuration parser
Home-page: http://devedge.bour.cc/wiki/PyerConf
Author: Guillaume Bour
Author-email: guillaume@bour.cc
License: GNU General Public License v3
Download-URL: http://devedge.bour.cc/resources/pyerconf/src/pyerconf.latest.tar.gz
Platform: UNKNOWN
Classifier: Development Status :: 4 - Beta
Classifier: Environment :: Console
Classifier: Environment :: X11 Applications
Classifier: Intended Audience :: Developers
Classifier: License :: OSI Approved :: GNU General Public License (GPL)
Classifier: Natural Language :: English
Classifier: Natural Language :: French
Classifier: Operating System :: OS Independent
Classifier: Programming Language :: Python
Classifier: Programming Language :: Python :: 2.5
Classifier: Programming Language :: Python :: 2.6
Classifier: Programming Language :: Python :: 2.7
Classifier: Topic :: Software Development :: Libraries
Classifier: Topic :: Software Development :: Libraries :: Python Modules
